tasgnss/__init__.py
tasgnss/core.py
tasgnss/core_bak.py
tasgnss/core_dev.py
tasgnss-0.1.5.dist-info/METADATA
tasgnss-0.1.5.dist-info/WHEEL
tasgnss-0.1.5.dist-info/top_level.txt
tasgnss-0.1.5.dist-info/RECORD
