Metadata-Version: 2.4
Name: tasgnss
Version: 0.1.5
Summary: A Python package for GNSS positioning and processing by TASLAB
Home-page: https://github.com/PolyU-TASLAB/TASGNSS
Author: Runzhi Hu
Author-email: run-zhi.hu@connect.polyu.hk
Classifier: Development Status :: 3 - Alpha
Classifier: Intended Audience :: Developers
Classifier: License :: OSI Approved :: MIT License
Classifier: Programming Language :: Python :: 3
Classifier: Programming Language :: Python :: 3.7
Classifier: Programming Language :: Python :: 3.8
Classifier: Programming Language :: Python :: 3.9
Classifier: Programming Language :: Python :: 3.10
Classifier: Programming Language :: Python :: 3.11
Classifier: Programming Language :: Python :: 3.12
Classifier: Programming Language :: Python :: 3.13
Requires-Python: >=3.7
Requires-Dist: pyrtklib
Requires-Dist: numpy
Requires-Dist: pymap3d
Dynamic: author
Dynamic: author-email
Dynamic: classifier
Dynamic: description
Dynamic: description-content-type
Dynamic: home-page
Dynamic: requires-dist
Dynamic: requires-python
Dynamic: summary
